tms_kit-0.4.1.dist-info/METADATA
tms_kit-0.4.1.dist-info/WHEEL
tms_kit-0.4.1.dist-info/entry_points.txt
tms_kit/__init__.py
tms_kit/data.py
tms_kit/loss.py
tms_kit/model.py
tms_kit/optimize.py
tms_kit/sae.py
tms_kit/tms.py
tms_kit/utils/device.py
tms_kit/utils/plotly.py
tms_kit/utils/utils.py
tms_kit-0.4.1.dist-info/RECORD
